[
  {
    "id": 712,
    "scientific_name": "Ailuropoda melanoleuca",
    "conservation_status": "VU",
    "group": "MAMMALIA",
    "iso_code": "CN",
    "common_name": "Giant Panda"
  },
  {
    "id": 16892,
    "scientific_name": "Phascolarctos cinereus",
    "conservation_status": "VU",
    "group": "MAMMALIA",
    "iso_code": "AU",
    "common_name": "Koala"
  },
  {
    "id": 12119,
    "scientific_name": "Lipotes vexillifer",
    "conservation_status": "CR",
    "group": "MAMMALIA",
    "iso_code": "CN",
    "common_name": "Yangtze River Dolphin"
  },
  {
    "id": 22705787,
    "scientific_name": "Urocissa ornata",
    "conservation_status": "VU",
    "group": "MAMMALIA",
    "iso_code": "LK",
    "common_name": "Sri Lanka Blue Magpie"
  },
  {
    "id": 58567,
    "scientific_name": "Pelophylax cerigensis",
    "conservation_status": "CR",
    "group": "AMPHIBIA",
    "iso_code": "GR",
    "common_name": "Karpathos Frog"
  },
  {
    "id": 29432,
    "scientific_name": "Ameerega planipaleae",
    "conservation_status": "CR",
    "group": "AMPHIBIA",
    "iso_code": "PE",
    "common_name": "Oxapampa Poison Frog"
  },
  {
    "id": 22046,
    "scientific_name": "Tragelaphus buxtoni",
    "conservation_status": "EN",
    "group": "MAMMALIA",
    "iso_code": "ET",
    "common_name": "Mountain Nyala"
  },
  {
    "id": 43899,
    "scientific_name": "Alouatta palliata ssp. coibensis",
    "conservation_status": "EN",
    "group": "MAMMALIA",
    "iso_code": "PA",
    "common_name": "Coiba Island Howler Monkey"
  },
  {
    "id": 11496,
    "scientific_name": "Lemur catta",
    "conservation_status": "EN",
    "group": "MAMMALIA",
    "iso_code": "MG",
    "common_name": "Ring-tailed Lemur"
  },
  {
    "id": 19819,
    "scientific_name": "Saguinus leucopus",
    "conservation_status": "VU",
    "group": "MAMMALIA",
    "iso_code": "CO",
    "common_name": "Silvery-brown Tamarin"
  },
  {
    "id": 196661,
    "scientific_name": "Varanus juxtindicus",
    "conservation_status": "LC",
    "group": "REPTILIA",
    "iso_code": "SB",
    "common_name": "Rennell Island Monitor"
  },
  {
    "id": 22728410,
    "scientific_name": "Antilophia bokermanni",
    "conservation_status": "CR",
    "group": "AVES",
    "iso_code": "BR",
    "common_name": "Araripe Manakin"
  },
  {
    "id": 136777,
    "scientific_name": "Natalus primus",
    "conservation_status": "VU",
    "group": "MAMMALIA",
    "iso_code": "CU",
    "common_name": "Cuban Greater Funnel-eared Bat"
  },
  {
    "id": 193482,
    "scientific_name": "Calumma tarzan",
    "conservation_status": "CR",
    "group": "REPTILIA",
    "iso_code": "MG",
    "common_name": "Calumma tarzan"
  },
  {
    "id": 5962,
    "scientific_name": "Cuora trifasciata",
    "conservation_status": "CR",
    "group": "REPTILIA",
    "iso_code": "CN",
    "common_name": "Cuora trifasciata"
  },
  {
    "id": 19495,
    "scientific_name": "rhinoceros sondaicus",
    "conservation_status": "CR",
    "group": "MAMMALIA",
    "iso_code": "BD",
    "common_name": "Javan Rhinoceros"
  },
  {
    "id": 6553,
    "scientific_name": "Dicerorhinus sumatrensis",
    "conservation_status": "CR",
    "group": "MAMMALIA",
    "iso_code": "BD",
    "common_name": "Sumatran Rhinoceros"
  },
  {
    "id": 21975,
    "scientific_name": "Tolypeutes tricinctus",
    "conservation_status": "VU",
    "group": "MAMMALIA",
    "iso_code": "BR",
    "common_name": "Brazilian Three-banded Armadillo"
  },
  {
    "id": 49002226,
    "scientific_name": "Nepenthes rigidifolia",
    "conservation_status": "CR",
    "group": "MAGNOLIOPSIDA",
    "iso_code": "ID",
    "common_name": "Nepenthes rigidifolia"
  },
  {
    "id": 10355,
    "scientific_name": "Bokermannohyla izecksohni",
    "conservation_status": "CR",
    "group": "AMPHIBIA",
    "iso_code": "BR",
    "common_name": "Izecksohn's Treefrog"
  },
  {
    "id": 22698691,
    "scientific_name": "Pitta megarhyncha",
    "conservation_status": "NT",
    "group": "AVES",
    "iso_code": "BD",
    "common_name": "Mangrove Pitta"
  },
  {
    "id": 4162,
    "scientific_name": "Cephalorhynchus hectori",
    "conservation_status": "EN",
    "group": "MAMMALIA",
    "iso_code": "NZ",
    "common_name": "Hector's Dolphin"
  },
  {
    "id": 984,
    "scientific_name": "Amanipodagrion gilliesi",
    "conservation_status": "CR",
    "group": "INSECTA",
    "iso_code": "TZ",
    "common_name": "Amanipodagrion gilliesi"
  },
  {
    "id": 3172,
    "scientific_name": "Incilius periglenes",
    "conservation_status": "EX",
    "group": "AMPHIBIA",
    "iso_code": "CR",
    "common_name": "Golden Toad"
  },
  {
    "id": 58979,
    "scientific_name": "Rhacophorus bifasciatus",
    "conservation_status": "NT",
    "group": "AMPHIBIA",
    "iso_code": "ID",
    "common_name": "Rhacophorus bifasciatus"
  },
  {
    "id": 18267,
    "scientific_name": "Procyon pygmaeus",
    "conservation_status": "CR",
    "group": "MAMMALIA",
    "iso_code": "MX",
    "common_name": "Pygmy Raccoon"
  },
  {
    "id": 199541,
    "scientific_name": "Seselphisis visenda",
    "conservation_status": "EN",
    "group": "INSECTA",
    "iso_code": "SC",
    "common_name": "Seychelles Predatory Bush-Cricket"
  },
  {
    "id": 39149,
    "scientific_name": "Cryptomeria japonica",
    "conservation_status": "NT",
    "group": "PINOPSIDA",
    "iso_code": "JP",
    "common_name": "Japanese Cedar"
  },
  {
    "id": 2057,
    "scientific_name": "Arctocephalus galapagoensis",
    "conservation_status": "EN",
    "group": "MAMMALIA",
    "iso_code": "EC",
    "common_name": "Galápagos Fur Seal"
  },
  {
    "id": 22685760,
    "scientific_name": "Ognorhynchus icterotis",
    "conservation_status": "EN",
    "group": "AVES",
    "iso_code": "CO",
    "common_name": "Yellow-eared Parrot"
  },
  {
    "id": 14760,
    "scientific_name": "Nicrophorus americanus",
    "conservation_status": "CR",
    "group": "INSECTA",
    "iso_code": "US",
    "common_name": "American Burying Beetle"
  },
  {
    "id": 41690,
    "scientific_name": "Arctictis binturong",
    "conservation_status": "VU",
    "group": "MAMMALIA",
    "iso_code": "BD",
    "common_name": "Binturong"
  },
  {
    "id": 32916,
    "scientific_name": "Erythrina schliebenii",
    "conservation_status": "CR",
    "group": "MAGNOLIOPSIDA",
    "iso_code": "TZ",
    "common_name": "Erythrina schliebenii"
  },
  {
    "id": 61425,
    "scientific_name": "Archaius tigris",
    "conservation_status": "EN",
    "group": "REPTILIA",
    "iso_code": "SC",
    "common_name": "Tiger Chameleon"
  },
  {
    "id": 15050,
    "scientific_name": "Ochotona iliensis",
    "conservation_status": "EN",
    "group": "MAMMALIA",
    "iso_code": "CN",
    "common_name": "Ili Pika"
  },
  {
    "id": 21247820,
    "scientific_name": "Bertia cambojiensis",
    "conservation_status": "CR",
    "group": "GASTROPODA",
    "iso_code": "VN",
    "common_name": "Bertia cambojiensis"
  },
  {
    "id": 30385,
    "scientific_name": "Clianthus puniceus",
    "conservation_status": "EN",
    "group": "MAGNOLIOPSIDA",
    "iso_code": "NZ",
    "common_name": "kākā beak"
  },
  {
    "id": 22806,
    "scientific_name": "Uromys rex",
    "conservation_status": "EN",
    "group": "MAMMALIA",
    "iso_code": "SB",
    "common_name": "King Rat"
  },
  {
    "id": 178627,
    "scientific_name": "Bitis peringueyi",
    "conservation_status": "LC",
    "group": "REPTILIA",
    "iso_code": "NA",
    "common_name": "Peringuey's Adder"
  },
  {
    "id": 34298,
    "scientific_name": "Brachyglottis huntii",
    "conservation_status": "VU",
    "group": "MAGNOLIOPSIDA",
    "iso_code": "NZ",
    "common_name": "Chatham Island Christmas tree"
  },
  {
    "id": 45353580,
    "scientific_name": "Apteryx mantelli",
    "conservation_status": "VU",
    "group": "AVES",
    "iso_code": "NZ",
    "common_name": "North Island Brown Kiwi"
  },
  {
    "id": 38465,
    "scientific_name": "Carpoxylon macrospermum",
    "conservation_status": "CR",
    "group": "LILIOPSIDA",
    "iso_code": "VU",
    "common_name": "Carpoxylon macrospermum"
  },
  {
    "id": 165861,
    "scientific_name": "Holacanthus clarionensis",
    "conservation_status": "VU",
    "group": "ACTINOPTERYGII",
    "iso_code": "MX",
    "common_name": "Clarion Angelfish"
  },
  {
    "id": 172861,
    "scientific_name": "Calumma nasutum",
    "conservation_status": "LC",
    "group": "REPTILIA",
    "iso_code": "MG",
    "common_name": "Nose-horned Chameleon"
  },
  {
    "id": 3036,
    "scientific_name": "Bradypus torquatus",
    "conservation_status": "VU",
    "group": "MAMMALIA",
    "iso_code": "BR",
    "common_name": "Maned Three-toed Sloth"
  },
  {
    "id": 12559,
    "scientific_name": "Macaca silenus",
    "conservation_status": "EN",
    "group": "MAMMALIA",
    "iso_code": "IN",
    "common_name": "Lion-tailed Macaque"
  },
  {
    "id": 169395,
    "scientific_name": "Zoogoneticus tequila",
    "conservation_status": "CR",
    "group": "ACTINOPTERYGII",
    "iso_code": "MX",
    "common_name": "Tequila Splitfin"
  },
  {
    "id": 38723,
    "scientific_name": "Voanioala gerardii",
    "conservation_status": "CR",
    "group": "LILIOPSIDA",
    "iso_code": "MG",
    "common_name": "Voanioala gerardii"
  },
  {
    "id": 136372,
    "scientific_name": "Vandeleuria nilagirica",
    "conservation_status": "EN",
    "group": "MAMMALIA",
    "iso_code": "IN",
    "common_name": "Nilgiri Long-tailed Tree Mouse"
  },
  {
    "id": 19750,
    "scientific_name": "Rousettus madagascariensis",
    "conservation_status": "NT",
    "group": "MAMMALIA",
    "iso_code": "MG",
    "common_name": "Madagascan Rousette"
  },
  {
    "id": 136309,
    "scientific_name": "Rhynchocyon udzungwensis",
    "conservation_status": "VU",
    "group": "MAMMALIA",
    "iso_code": "TZ",
    "common_name": "Grey-faced Sengi"
  },
  {
    "id": 19705,
    "scientific_name": "Rhynchocyon chrysopygus",
    "conservation_status": "EN",
    "group": "MAMMALIA",
    "iso_code": "KE",
    "common_name": "Golden-rumped Sengi"
  },
  {
    "id": 22694103,
    "scientific_name": "Rhinoptilus bitorquatus",
    "conservation_status": "CR",
    "group": "AVES",
    "iso_code": "IN",
    "common_name": "Jerdon's Courser"
  },
  {
    "id": 30732,
    "scientific_name": "Quercus hintonii",
    "conservation_status": "CR",
    "group": "MAGNOLIOPSIDA",
    "iso_code": "MX",
    "common_name": "Encino prieto "
  },
  {
    "id": 41586,
    "scientific_name": "Pseudalopex fulvipes",
    "conservation_status": "EN",
    "group": "MAMMALIA",
    "iso_code": "CL",
    "common_name": "Darwin's Fox"
  },
  {
    "id": 17902,
    "scientific_name": "Polposipus herculeanus",
    "conservation_status": "VU",
    "group": "INSECTA",
    "iso_code": "SC",
    "common_name": "Frigate Island Giant Tenebrionid Beetle"
  },
  {
    "id": 22696012,
    "scientific_name": "Pithecophaga jefferyi",
    "conservation_status": "CR",
    "group": "AVES",
    "iso_code": "PH",
    "common_name": "Philippine Eagle"
  },
  {
    "id": 33924,
    "scientific_name": "Pinus rzedowskii",
    "conservation_status": "VU",
    "group": "PINOPSIDA",
    "iso_code": "MX",
    "common_name": "Rzedowski's Pine"
  },
  {
    "id": 15419,
    "scientific_name": "Orcaella brevirostris",
    "conservation_status": "EN",
    "group": "MAMMALIA",
    "iso_code": "AU",
    "common_name": "Irrawaddy Dolphin"
  },
  {
    "id": 15188,
    "scientific_name": "Okapia johnstoni",
    "conservation_status": "EN",
    "group": "MAMMALIA",
    "iso_code": "CD",
    "common_name": "Okapi"
  },
  {
    "id": 14709,
    "scientific_name": "Nesoryzomys swarthi",
    "conservation_status": "VU",
    "group": "MAMMALIA",
    "iso_code": "EC",
    "common_name": "Santiago Galapagos Mouse"
  },
  {
    "id": 54837,
    "scientific_name": "Nectophrynoides asperginis",
    "conservation_status": "EW",
    "group": "AMPHIBIA",
    "iso_code": "TZ",
    "common_name": "Kihansi Spray Toad"
  },
  {
    "id": 1089,
    "scientific_name": "Neamblysomus julianae",
    "conservation_status": "EN",
    "group": "MAMMALIA",
    "iso_code": "ZA",
    "common_name": "Juliana's Golden Mole"
  },
  {
    "id": 14288,
    "scientific_name": "Myzopoda aurita",
    "conservation_status": "LC",
    "group": "MAMMALIA",
    "iso_code": "MG",
    "common_name": "Eastern Sucker-footed Bat"
  },
  {
    "id": 14136,
    "scientific_name": "Myotis sodalis",
    "conservation_status": "NT",
    "group": "MAMMALIA",
    "iso_code": "US",
    "common_name": "Indiana Bat"
  },
  {
    "id": 22711063,
    "scientific_name": "Mimus trifasciatus",
    "conservation_status": "EN",
    "group": "AVES",
    "iso_code": "EC",
    "common_name": "Floreana Mockingbird"
  },
  {
    "id": 42107,
    "scientific_name": "Microcycas calocoma",
    "conservation_status": "CR",
    "group": "CYCADOPSIDA",
    "iso_code": "CU",
    "common_name": "Cork Palm"
  },
  {
    "id": 19672693,
    "scientific_name": "Ixalidium transiens",
    "conservation_status": "VU",
    "group": "INSECTA",
    "iso_code": "TZ",
    "common_name": "Usambara Drumming Grasshopper"
  },
  {
    "id": 187435,
    "scientific_name": "Halichoeres socialis",
    "conservation_status": "EN",
    "group": "ACTINOPTERYGII",
    "iso_code": "BZ",
    "common_name": "Social Wrasse"
  },
  {
    "id": 4967,
    "scientific_name": "Glyptemys muhlenbergii",
    "conservation_status": "CR",
    "group": "REPTILIA",
    "iso_code": "US",
    "common_name": "Bog Turtle"
  },
  {
    "id": 22721839,
    "scientific_name": "Geothlypis beldingi",
    "conservation_status": "VU",
    "group": "AVES",
    "iso_code": "MX",
    "common_name": "Belding's Yellowthroat"
  },
  {
    "id": 43995,
    "scientific_name": "Erioderma pedicellatum",
    "conservation_status": "CR",
    "group": "LECANOROMYCETES",
    "iso_code": "CA",
    "common_name": "Boreal Felt Lichen"
  },
  {
    "id": 7866,
    "scientific_name": "Epioblasma capsaeformis",
    "conservation_status": "EN",
    "group": "BIVALVIA",
    "iso_code": "US",
    "common_name": "Oyster Mussel"
  },
  {
    "id": 41889,
    "scientific_name": "Encephalartos hirsutus",
    "conservation_status": "CR",
    "group": "CYCADOPSIDA",
    "iso_code": "ZA",
    "common_name": "Venda Cycad"
  },
  {
    "id": 158613,
    "scientific_name": "Ecnomiohyla rabborum",
    "conservation_status": "CR",
    "group": "AMPHIBIA",
    "iso_code": "PA",
    "common_name": "Ecnomiohyla rabborum"
  },
  {
    "id": 6852,
    "scientific_name": "Dryococelus australis",
    "conservation_status": "CR",
    "group": "INSECTA",
    "iso_code": "AU",
    "common_name": "Lord Howe Island Stick-insect"
  },
  {
    "id": 6306,
    "scientific_name": "Deinacrida rugosa",
    "conservation_status": "VU",
    "group": "INSECTA",
    "iso_code": "NZ",
    "common_name": "Stephens Island Weta"
  },
  {
    "id": 5957,
    "scientific_name": "Cuora yunnanensis",
    "conservation_status": "CR",
    "group": "REPTILIA",
    "iso_code": "CN",
    "common_name": "Yunnan Box Turtle"
  },
  {
    "id": 5760,
    "scientific_name": "Cryptoprocta ferox",
    "conservation_status": "VU",
    "group": "MAMMALIA",
    "iso_code": "MG",
    "common_name": "Fossa"
  },
  {
    "id": 30366,
    "scientific_name": "Cryosophila williamsii",
    "conservation_status": "EW",
    "group": "LILIOPSIDA",
    "iso_code": "HN",
    "common_name": "Root-spine Palm"
  },
  {
    "id": 22728472,
    "scientific_name": "Centrocercus minimus",
    "conservation_status": "EN",
    "group": "AVES",
    "iso_code": "US",
    "common_name": "Gunnison Grouse"
  },
  {
    "id": 3989,
    "scientific_name": "Casarea dussumieri",
    "conservation_status": "EN",
    "group": "REPTILIA",
    "iso_code": "MU",
    "common_name": "Keel-scaled Boa"
  },
  {
    "id": 22689809,
    "scientific_name": "Antrostomus noctitherus",
    "conservation_status": "EN",
    "group": "AVES",
    "iso_code": "PR",
    "common_name": "Puerto Rican Nightjar"
  },
  {
    "id": 61618,
    "scientific_name": "Calendula maritima",
    "conservation_status": "CR",
    "group": "MAGNOLIOPSIDA",
    "iso_code": "IT",
    "common_name": "Sea Marigold"
  },
  {
    "id": 3083,
    "scientific_name": "Brookesia perarmata",
    "conservation_status": "EN",
    "group": "REPTILIA",
    "iso_code": "MG",
    "common_name": "Antsingy Leaf Chameleon"
  },
  {
    "id": 135295,
    "scientific_name": "Bombus franklini",
    "conservation_status": "CR",
    "group": "INSECTA",
    "iso_code": "US",
    "common_name": "Franklin's Bumble Bee"
  },
  {
    "id": 6234,
    "scientific_name": "Beatragus hunteri",
    "conservation_status": "CR",
    "group": "MAMMALIA",
    "iso_code": "KE",
    "common_name": "Hirola"
  },
  {
    "id": 10952,
    "scientific_name": "Batagur trivittata",
    "conservation_status": "EN",
    "group": "REPTILIA",
    "iso_code": "MM",
    "common_name": "Burmese Roofed Turtle"
  },
  {
    "id": 54444,
    "scientific_name": "Barbourula kalimantanensis",
    "conservation_status": "EN",
    "group": "AMPHIBIA",
    "iso_code": "ID",
    "common_name": "Bornean Flat-headed Frog"
  },
  {
    "id": 57703,
    "scientific_name": "Balebreviceps hillmani",
    "conservation_status": "CR",
    "group": "AMPHIBIA",
    "iso_code": "ET",
    "common_name": "Bale Mountains Treefrog"
  },
  {
    "id": 60286,
    "scientific_name": "Azuragrion granti",
    "conservation_status": "NT",
    "group": "INSECTA",
    "iso_code": "YE",
    "common_name": "Socotra Bluet"
  },
  {
    "id": 22680380,
    "scientific_name": "Aythya innotata",
    "conservation_status": "CR",
    "group": "AVES",
    "iso_code": "MG",
    "common_name": "Madagascar Pochard"
  },
  {
    "id": 9016,
    "scientific_name": "Astrochelys yniphora",
    "conservation_status": "CR",
    "group": "REPTILIA",
    "iso_code": "MG",
    "common_name": "Ploughshare Tortoise"
  },
  {
    "id": 16559,
    "scientific_name": "Pentalagus furnessi",
    "conservation_status": "EN",
    "group": "MAMMALIA",
    "iso_code": "JP",
    "common_name": "Amami Rabbit"
  },
  {
    "id": 56765,
    "scientific_name": "Craugastor milesi",
    "conservation_status": "CR",
    "group": "AMPHIBIA",
    "iso_code": "HN",
    "common_name": "Miles' Robber Frog"
  },
  {
    "id": 63563,
    "scientific_name": "Poecilotheria metallica",
    "conservation_status": "CR",
    "group": "ARACHNIDA",
    "iso_code": "IN",
    "common_name": "Peacock Tarantula"
  },
  {
    "id": 55219,
    "scientific_name": "Ameerega cainarachi",
    "conservation_status": "VU",
    "group": "AMPHIBIA",
    "iso_code": "PE",
    "common_name": "Cainarachi Poison Frog"
  },
  {
    "id": 22717428,
    "scientific_name": "Alauda razae",
    "conservation_status": "CR",
    "group": "AVES",
    "iso_code": "CV",
    "common_name": "Raso Lark"
  },
  {
    "id": 867,
    "scientific_name": "Alligator sinensis",
    "conservation_status": "CR",
    "group": "REPTILIA",
    "iso_code": "CN",
    "common_name": "Chinese Alligator"
  },
  {
    "id": 1095,
    "scientific_name": "Ambystoma mexicanum",
    "conservation_status": "CR",
    "group": "AMPHIBIA",
    "iso_code": "MX",
    "common_name": "Axolotl"
  }
]