[
  {
    "id": "712",
    "name": "Ailuropoda melanoleuca",
    "status": "VU",
    "group": "MAMMALIA",
    "code": "CN",
    "commonName": "Giant Panda"
  },
  {
    "id": "16892",
    "name": "Phascolarctos cinereus",
    "status": "VU",
    "group": "MAMMALIA",
    "code": "AU",
    "commonName": "Koala"
  },
  {
    "id": "12119",
    "name": "Lipotes vexillifer",
    "status": "CR",
    "group": "MAMMALIA",
    "code": "CN",
    "commonName": "Yangtze River Dolphin"
  },
  {
    "id": "22705787",
    "name": "Urocissa ornata",
    "status": "VU",
    "group": "MAMMALIA",
    "code": "LK",
    "commonName": "Sri Lanka Blue Magpie"
  },
  {
    "id": "58567",
    "name": "Pelophylax cerigensis",
    "status": "CR",
    "group": "AMPHIBIA",
    "code": "GR",
    "commonName": "Karpathos Frog"
  },
  {
    "id": "29432",
    "name": "Ameerega planipaleae",
    "status": "CR",
    "group": "AMPHIBIA",
    "code": "PE",
    "commonName": "Oxapampa Poison Frog"
  },
  {
    "id": "22046",
    "name": "Tragelaphus buxtoni",
    "status": "EN",
    "group": "MAMMALIA",
    "code": "ET",
    "commonName": "Mountain Nyala"
  },
  {
    "id": "43899",
    "name": "Alouatta palliata ssp. coibensis",
    "status": "EN",
    "group": "MAMMALIA",
    "code": "PA",
    "commonName": "Coiba Island Howler Monkey"
  },
  {
    "id": "11496",
    "name": "Lemur catta",
    "status": "EN",
    "group": "MAMMALIA",
    "code": "MG",
    "commonName": "Ring-tailed Lemur"
  },
  {
    "id": "19819",
    "name": "Saguinus leucopus",
    "status": "VU",
    "group": "MAMMALIA",
    "code": "CO",
    "commonName": "Silvery-brown Tamarin"
  },
  {
    "id": "196661",
    "name": "Varanus juxtindicus",
    "status": "LC",
    "group": "REPTILIA",
    "code": "SB",
    "commonName": "Rennell Island Monitor"
  },
  {
    "id": "22728410",
    "name": "Antilophia bokermanni",
    "status": "CR",
    "group": "AVES",
    "code": "BR",
    "commonName": "Araripe Manakin"
  },
  {
    "id": "136777",
    "name": "Natalus primus",
    "status": "VU",
    "group": "MAMMALIA",
    "code": "CU",
    "commonName": "Cuban Greater Funnel-eared Bat"
  },
  {
    "id": "193482",
    "name": "Calumma tarzan",
    "status": "CR",
    "group": "REPTILIA",
    "code": "MG",
    "commonName": "Calumma tarzan"
  },
  {
    "id": "5962",
    "name": "Cuora trifasciata",
    "status": "CR",
    "group": "REPTILIA",
    "code": "CN",
    "commonName": "Cuora trifasciata"
  },
  {
    "id": "19495",
    "name": "rhinoceros sondaicus",
    "status": "CR",
    "group": "MAMMALIA",
    "code": "BD",
    "commonName": "Javan Rhinoceros"
  },
  {
    "id": "6553",
    "name": "Dicerorhinus sumatrensis",
    "status": "CR",
    "group": "MAMMALIA",
    "code": "BD",
    "commonName": "Sumatran Rhinoceros"
  },
  {
    "id": "21975",
    "name": "Tolypeutes tricinctus",
    "status": "VU",
    "group": "MAMMALIA",
    "code": "BR",
    "commonName": "Brazilian Three-banded Armadillo"
  },
  {
    "id": "49002226",
    "name": "Nepenthes rigidifolia",
    "status": "CR",
    "group": "MAGNOLIOPSIDA",
    "code": "ID",
    "commonName": "Nepenthes rigidifolia"
  },
  {
    "id": "10355",
    "name": "Bokermannohyla izecksohni",
    "status": "CR",
    "group": "AMPHIBIA",
    "code": "BR",
    "commonName": "Izecksohn's Treefrog"
  },
  {
    "id": "22698691",
    "name": "Pitta megarhyncha",
    "status": "NT",
    "group": "AVES",
    "code": "BD",
    "commonName": "Mangrove Pitta"
  },
  {
    "id": "4162",
    "name": "Cephalorhynchus hectori",
    "status": "EN",
    "group": "MAMMALIA",
    "code": "NZ",
    "commonName": "Hector's Dolphin"
  },
  {
    "id": "984",
    "name": "Amanipodagrion gilliesi",
    "status": "CR",
    "group": "INSECTA",
    "code": "TZ",
    "commonName": "Amanipodagrion gilliesi"
  },
  {
    "id": "3172",
    "name": "Incilius periglenes",
    "status": "EX",
    "group": "AMPHIBIA",
    "code": "CR",
    "commonName": "Golden Toad"
  },
  {
    "id": "58979",
    "name": "Rhacophorus bifasciatus",
    "status": "NT",
    "group": "AMPHIBIA",
    "code": "ID",
    "commonName": "Rhacophorus bifasciatus"
  },
  {
    "id": "18267",
    "name": "Procyon pygmaeus",
    "status": "CR",
    "group": "MAMMALIA",
    "code": "MX",
    "commonName": "Pygmy Raccoon"
  },
  {
    "id": "199541",
    "name": "Seselphisis visenda",
    "status": "EN",
    "group": "INSECTA",
    "code": "SC",
    "commonName": "Seychelles Predatory Bush-Cricket"
  },
  {
    "id": "39149",
    "name": "Cryptomeria japonica",
    "status": "NT",
    "group": "PINOPSIDA",
    "code": "JP",
    "commonName": "Japanese Cedar"
  },
  {
    "id": "2057",
    "name": "Arctocephalus galapagoensis",
    "status": "EN",
    "group": "MAMMALIA",
    "code": "EC",
    "commonName": "Galápagos Fur Seal"
  },
  {
    "id": "22685760",
    "name": "Ognorhynchus icterotis",
    "status": "EN",
    "group": "AVES",
    "code": "CO",
    "commonName": "Yellow-eared Parrot"
  },
  {
    "id": "14760",
    "name": "Nicrophorus americanus",
    "status": "CR",
    "group": "INSECTA",
    "code": "US",
    "commonName": "American Burying Beetle"
  },
  {
    "id": "41690",
    "name": "Arctictis binturong",
    "status": "VU",
    "group": "MAMMALIA",
    "code": "BD",
    "commonName": "Binturong"
  },
  {
    "id": "32916",
    "name": "Erythrina schliebenii",
    "status": "CR",
    "group": "MAGNOLIOPSIDA",
    "code": "TZ",
    "commonName": "Erythrina schliebenii"
  },
  {
    "id": "61425",
    "name": "Archaius tigris",
    "status": "EN",
    "group": "REPTILIA",
    "code": "SC",
    "commonName": "Tiger Chameleon"
  },
  {
    "id": "15050",
    "name": "Ochotona iliensis",
    "status": "EN",
    "group": "MAMMALIA",
    "code": "CN",
    "commonName": "Ili Pika"
  },
  {
    "id": "21247820",
    "name": "Bertia cambojiensis",
    "status": "CR",
    "group": "GASTROPODA",
    "code": "VN",
    "commonName": "Bertia cambojiensis"
  },
  {
    "id": "30385",
    "name": "Clianthus puniceus",
    "status": "EN",
    "group": "MAGNOLIOPSIDA",
    "code": "NZ",
    "commonName": "kākā beak"
  },
  {
    "id": "22806",
    "name": "Uromys rex",
    "status": "EN",
    "group": "MAMMALIA",
    "code": "SB",
    "commonName": "King Rat"
  },
  {
    "id": "178627",
    "name": "Bitis peringueyi",
    "status": "LC",
    "group": "REPTILIA",
    "code": "NA",
    "commonName": "Peringuey's Adder"
  },
  {
    "id": "34298",
    "name": "Brachyglottis huntii",
    "status": "VU",
    "group": "MAGNOLIOPSIDA",
    "code": "NZ",
    "commonName": "Chatham Island Christmas tree"
  },
  {
    "id": "45353580",
    "name": "Apteryx mantelli",
    "status": "VU",
    "group": "AVES",
    "code": "NZ",
    "commonName": "North Island Brown Kiwi"
  },
  {
    "id": "38465",
    "name": "Carpoxylon macrospermum",
    "status": "CR",
    "group": "LILIOPSIDA",
    "code": "VU",
    "commonName": "Carpoxylon macrospermum"
  },
  {
    "id": "165861",
    "name": "Holacanthus clarionensis",
    "status": "VU",
    "group": "ACTINOPTERYGII",
    "code": "MX",
    "commonName": "Clarion Angelfish"
  },
  {
    "id": "172861",
    "name": "Calumma nasutum",
    "status": "LC",
    "group": "REPTILIA",
    "code": "MG",
    "commonName": "Nose-horned Chameleon"
  },
  {
    "id": "3036",
    "name": "Bradypus torquatus",
    "status": "VU",
    "group": "MAMMALIA",
    "code": "BR",
    "commonName": "Maned Three-toed Sloth"
  },
  {
    "id": "12559",
    "name": "Macaca silenus",
    "status": "EN",
    "group": "MAMMALIA",
    "code": "IN",
    "commonName": "Lion-tailed Macaque"
  },
  {
    "id": "169395",
    "name": "Zoogoneticus tequila",
    "status": "CR",
    "group": "ACTINOPTERYGII",
    "code": "MX",
    "commonName": "Tequila Splitfin"
  },
  {
    "id": "38723",
    "name": "Voanioala gerardii",
    "status": "CR",
    "group": "LILIOPSIDA",
    "code": "MG",
    "commonName": "Voanioala gerardii"
  },
  {
    "id": "136372",
    "name": "Vandeleuria nilagirica",
    "status": "EN",
    "group": "MAMMALIA",
    "code": "IN",
    "commonName": "Nilgiri Long-tailed Tree Mouse"
  },
  {
    "id": "19750",
    "name": "Rousettus madagascariensis",
    "status": "NT",
    "group": "MAMMALIA",
    "code": "MG",
    "commonName": "Madagascan Rousette"
  },
  {
    "id": "136309",
    "name": "Rhynchocyon udzungwensis",
    "status": "VU",
    "group": "MAMMALIA",
    "code": "TZ",
    "commonName": "Grey-faced Sengi"
  },
  {
    "id": "19705",
    "name": "Rhynchocyon chrysopygus",
    "status": "EN",
    "group": "MAMMALIA",
    "code": "KE",
    "commonName": "Golden-rumped Sengi"
  },
  {
    "id": "22694103",
    "name": "Rhinoptilus bitorquatus",
    "status": "CR",
    "group": "AVES",
    "code": "IN",
    "commonName": "Jerdon's Courser"
  },
  {
    "id": "30732",
    "name": "Quercus hintonii",
    "status": "CR",
    "group": "MAGNOLIOPSIDA",
    "code": "MX",
    "commonName": "Encino prieto "
  },
  {
    "id": "41586",
    "name": "Pseudalopex fulvipes",
    "status": "EN",
    "group": "MAMMALIA",
    "code": "CL",
    "commonName": "Darwin's Fox"
  },
  {
    "id": "17902",
    "name": "Polposipus herculeanus",
    "status": "VU",
    "group": "INSECTA",
    "code": "SC",
    "commonName": "Frigate Island Giant Tenebrionid Beetle"
  },
  {
    "id": "22696012",
    "name": "Pithecophaga jefferyi",
    "status": "CR",
    "group": "AVES",
    "code": "PH",
    "commonName": "Philippine Eagle"
  },
  {
    "id": "33924",
    "name": "Pinus rzedowskii",
    "status": "VU",
    "group": "PINOPSIDA",
    "code": "MX",
    "commonName": "Rzedowski's Pine"
  },
  {
    "id": "15419",
    "name": "Orcaella brevirostris",
    "status": "EN",
    "group": "MAMMALIA",
    "code": "AU",
    "commonName": "Irrawaddy Dolphin"
  },
  {
    "id": "15188",
    "name": "Okapia johnstoni",
    "status": "EN",
    "group": "MAMMALIA",
    "code": "CD",
    "commonName": "Okapi"
  },
  {
    "id": "14709",
    "name": "Nesoryzomys swarthi",
    "status": "VU",
    "group": "MAMMALIA",
    "code": "EC",
    "commonName": "Santiago Galapagos Mouse"
  },
  {
    "id": "54837",
    "name": "Nectophrynoides asperginis",
    "status": "EW",
    "group": "AMPHIBIA",
    "code": "TZ",
    "commonName": "Kihansi Spray Toad"
  },
  {
    "id": "1089",
    "name": "Neamblysomus julianae",
    "status": "EN",
    "group": "MAMMALIA",
    "code": "ZA",
    "commonName": "Juliana's Golden Mole"
  },
  {
    "id": "14288",
    "name": "Myzopoda aurita",
    "status": "LC",
    "group": "MAMMALIA",
    "code": "MG",
    "commonName": "Eastern Sucker-footed Bat"
  },
  {
    "id": "14136",
    "name": "Myotis sodalis",
    "status": "NT",
    "group": "MAMMALIA",
    "code": "US",
    "commonName": "Indiana Bat"
  },
  {
    "id": "22711063",
    "name": "Mimus trifasciatus",
    "status": "EN",
    "group": "AVES",
    "code": "EC",
    "commonName": "Floreana Mockingbird"
  },
  {
    "id": "42107",
    "name": "Microcycas calocoma",
    "status": "CR",
    "group": "CYCADOPSIDA",
    "code": "CU",
    "commonName": "Cork Palm"
  },
  {
    "id": "19672693",
    "name": "Ixalidium transiens",
    "status": "VU",
    "group": "INSECTA",
    "code": "TZ",
    "commonName": "Usambara Drumming Grasshopper"
  },
  {
    "id": "187435",
    "name": "Halichoeres socialis",
    "status": "EN",
    "group": "ACTINOPTERYGII",
    "code": "BZ",
    "commonName": "Social Wrasse"
  },
  {
    "id": "4967",
    "name": "Glyptemys muhlenbergii",
    "status": "CR",
    "group": "REPTILIA",
    "code": "US",
    "commonName": "Bog Turtle"
  },
  {
    "id": "22721839",
    "name": "Geothlypis beldingi",
    "status": "VU",
    "group": "AVES",
    "code": "MX",
    "commonName": "Belding's Yellowthroat"
  },
  {
    "id": "43995",
    "name": "Erioderma pedicellatum",
    "status": "CR",
    "group": "LECANOROMYCETES",
    "code": "CA",
    "commonName": "Boreal Felt Lichen"
  },
  {
    "id": "7866",
    "name": "Epioblasma capsaeformis",
    "status": "EN",
    "group": "BIVALVIA",
    "code": "US",
    "commonName": "Oyster Mussel"
  },
  {
    "id": "41889",
    "name": "Encephalartos hirsutus",
    "status": "CR",
    "group": "CYCADOPSIDA",
    "code": "ZA",
    "commonName": "Venda Cycad"
  },
  {
    "id": "158613",
    "name": "Ecnomiohyla rabborum",
    "status": "CR",
    "group": "AMPHIBIA",
    "code": "PA",
    "commonName": "Ecnomiohyla rabborum"
  },
  {
    "id": "6852",
    "name": "Dryococelus australis",
    "status": "CR",
    "group": "INSECTA",
    "code": "AU",
    "commonName": "Lord Howe Island Stick-insect"
  },
  {
    "id": "6306",
    "name": "Deinacrida rugosa",
    "status": "VU",
    "group": "INSECTA",
    "code": "NZ",
    "commonName": "Stephens Island Weta"
  },
  {
    "id": "5957",
    "name": "Cuora yunnanensis",
    "status": "CR",
    "group": "REPTILIA",
    "code": "CN",
    "commonName": "Yunnan Box Turtle"
  },
  {
    "id": "5760",
    "name": "Cryptoprocta ferox",
    "status": "VU",
    "group": "MAMMALIA",
    "code": "MG",
    "commonName": "Fossa"
  },
  {
    "id": "30366",
    "name": "Cryosophila williamsii",
    "status": "EW",
    "group": "LILIOPSIDA",
    "code": "HN",
    "commonName": "Root-spine Palm"
  },
  {
    "id": "22728472",
    "name": "Centrocercus minimus",
    "status": "EN",
    "group": "AVES",
    "code": "US",
    "commonName": "Gunnison Grouse"
  },
  {
    "id": "3989",
    "name": "Casarea dussumieri",
    "status": "EN",
    "group": "REPTILIA",
    "code": "MU",
    "commonName": "Keel-scaled Boa"
  },
  {
    "id": "22689809",
    "name": "Antrostomus noctitherus",
    "status": "EN",
    "group": "AVES",
    "code": "PR",
    "commonName": "Puerto Rican Nightjar"
  },
  {
    "id": "61618",
    "name": "Calendula maritima",
    "status": "CR",
    "group": "MAGNOLIOPSIDA",
    "code": "IT",
    "commonName": "Sea Marigold"
  },
  {
    "id": "3083",
    "name": "Brookesia perarmata",
    "status": "EN",
    "group": "REPTILIA",
    "code": "MG",
    "commonName": "Antsingy Leaf Chameleon"
  },
  {
    "id": "135295",
    "name": "Bombus franklini",
    "status": "CR",
    "group": "INSECTA",
    "code": "US",
    "commonName": "Franklin's Bumble Bee"
  },
  {
    "id": "6234",
    "name": "Beatragus hunteri",
    "status": "CR",
    "group": "MAMMALIA",
    "code": "KE",
    "commonName": "Hirola"
  },
  {
    "id": "10952",
    "name": "Batagur trivittata",
    "status": "EN",
    "group": "REPTILIA",
    "code": "MM",
    "commonName": "Burmese Roofed Turtle"
  },
  {
    "id": "54444",
    "name": "Barbourula kalimantanensis",
    "status": "EN",
    "group": "AMPHIBIA",
    "code": "ID",
    "commonName": "Bornean Flat-headed Frog"
  },
  {
    "id": "57703",
    "name": "Balebreviceps hillmani",
    "status": "CR",
    "group": "AMPHIBIA",
    "code": "ET",
    "commonName": "Bale Mountains Treefrog"
  },
  {
    "id": "60286",
    "name": "Azuragrion granti",
    "status": "NT",
    "group": "INSECTA",
    "code": "YE",
    "commonName": "Socotra Bluet"
  },
  {
    "id": "22680380",
    "name": "Aythya innotata",
    "status": "CR",
    "group": "AVES",
    "code": "MG",
    "commonName": "Madagascar Pochard"
  },
  {
    "id": "9016",
    "name": "Astrochelys yniphora",
    "status": "CR",
    "group": "REPTILIA",
    "code": "MG",
    "commonName": "Ploughshare Tortoise"
  },
  {
    "id": "16559",
    "name": "Pentalagus furnessi",
    "status": "EN",
    "group": "MAMMALIA",
    "code": "JP",
    "commonName": "Amami Rabbit"
  },
  {
    "id": "56765",
    "name": "Craugastor milesi",
    "status": "CR",
    "group": "AMPHIBIA",
    "code": "HN",
    "commonName": "Miles' Robber Frog"
  },
  {
    "id": "63563",
    "name": "Poecilotheria metallica",
    "status": "CR",
    "group": "ARACHNIDA",
    "code": "IN",
    "commonName": "Peacock Tarantula"
  },
  {
    "id": "55219",
    "name": "Ameerega cainarachi",
    "status": "VU",
    "group": "AMPHIBIA",
    "code": "PE",
    "commonName": "Cainarachi Poison Frog"
  },
  {
    "id": "22717428",
    "name": "Alauda razae",
    "status": "CR",
    "group": "AVES",
    "code": "CV",
    "commonName": "Raso Lark"
  },
  {
    "id": "867",
    "name": "Alligator sinensis",
    "status": "CR",
    "group": "REPTILIA",
    "code": "CN",
    "commonName": "Chinese Alligator"
  },
  {
    "id": "1095",
    "name": "Ambystoma mexicanum",
    "status": "CR",
    "group": "AMPHIBIA",
    "code": "MX",
    "commonName": "Axolotl"
  }
]
